greeklish
greeklish/tests
